Metadata-Version: 2.1
Name: proxied-chromedriver-binary-auto
Version: 0.4
Summary: Installer for chromedriver.
Home-page: https://github.com/imanazari70/proxied-chromedriver-binary-auto
Author: Iman Azari
Author-email: azari@mahsan.co
License: MIT
Keywords: chromedriver chrome browser selenium splinter
Classifier: Development Status :: 5 - Production/Stable
Classifier: Topic :: Software Development :: Testing
Classifier: Topic :: System :: Installation/Setup
Classifier: Topic :: Software Development :: Libraries :: Python Modules
Classifier: License :: OSI Approved :: MIT License
License-File: LICENSE
